zuul/__init__.py
zuul/_setup_hook.py
zuul/change_matcher.py
zuul/configloader.py
zuul/exceptions.py
zuul/model.py
zuul/model_api.py
zuul/nodepool.py
zuul/scheduler.py
zuul/version.py
zuul/ansible/__init__.py
zuul/ansible/logconfig.py
zuul/ansible/paths.py
zuul/ansible/schema.py
zuul/ansible/stream_setup.py
zuul/ansible/win_zuul_console.cs
zuul/ansible/11/logconfig.py
zuul/ansible/11/paths.py
zuul/ansible/11/schema.py
zuul/ansible/11/stream_setup.py
zuul/ansible/11/win_zuul_console.cs
zuul/ansible/11/action/__init__.py
zuul/ansible/11/action/command.py
zuul/ansible/11/action/command.pyi
zuul/ansible/11/action/normal.py
zuul/ansible/11/action/win_zuul_console.py
zuul/ansible/11/action/zuul_freeze.py
zuul/ansible/11/action/zuul_return.py
zuul/ansible/11/callback/__init__.py
zuul/ansible/11/callback/zuul_json.py
zuul/ansible/11/callback/zuul_stream.py
zuul/ansible/11/callback/zuul_unreachable.py
zuul/ansible/11/filter/__init__.py
zuul/ansible/11/filter/zuul_filters.py
zuul/ansible/11/library/__init__.py
zuul/ansible/11/library/command.py
zuul/ansible/11/library/win_zuul_console.ps1
zuul/ansible/11/library/zuul_console.py
zuul/ansible/11/library/zuul_win_command.ps1
zuul/ansible/11/library/zuul_win_shell.ps1
zuul/ansible/11/library/module_utils/Ansible.ModuleUtils.Zuul.Win.Command.Process.psm1
zuul/ansible/11/library/module_utils/Ansible.ModuleUtils.Zuul.Win.Shell.CommandUtil.psm1
zuul/ansible/11/library/module_utils/Ansible.Zuul.Win.Command.Process.cs
zuul/ansible/11/library/module_utils/Ansible.Zuul.Win.Common.cs
zuul/ansible/11/library/module_utils/Ansible.Zuul.Win.Shell.Process.cs
zuul/ansible/11/library/module_utils/__init__.py
zuul/ansible/9/logconfig.py
zuul/ansible/9/paths.py
zuul/ansible/9/schema.py
zuul/ansible/9/stream_setup.py
zuul/ansible/9/win_zuul_console.cs
zuul/ansible/9/action/__init__.py
zuul/ansible/9/action/command.py
zuul/ansible/9/action/command.pyi
zuul/ansible/9/action/normal.py
zuul/ansible/9/action/win_zuul_console.py
zuul-13.1.1.dist-info/licenses/AUTHORS
zuul-13.1.1.dist-info/licenses/COPYING
zuul-13.1.1.dist-info/licenses/LICENSE
zuul-13.1.1.dist-info/METADATA
zuul-13.1.1.dist-info/WHEEL
zuul-13.1.1.dist-info/entry_points.txt
zuul-13.1.1.dist-info/pbr.json
zuul-13.1.1.dist-info/top_level.txt
zuul-13.1.1.dist-info/RECORD
