Metadata-Version: 2.4
Name: zuul
Version: 13.1.1
Summary: A Project Gating System
Home-page: https://zuul-ci.org/
Author: Zuul Team
Author-email: zuul-discuss@lists.zuul-ci.org
Classifier: Intended Audience :: Information Technology
Classifier: Intended Audience :: System Administrators
Classifier: License :: OSI Approved :: Apache Software License
Classifier: Operating System :: POSIX :: Linux
Classifier: Programming Language :: Python
Classifier: Programming Language :: Python :: 3
Classifier: Programming Language :: Python :: 3.11
Classifier: Programming Language :: Python :: 3.12
Requires-Python: >=3.11
License-File: LICENSE
License-File: COPYING
License-File: AUTHORS
Requires-Dist: pbr>=1.1.0
Requires-Dist: virtualenv!=20.0.0,!=20.0.1,>20
Requires-Dist: python-dateutil
Requires-Dist: github3.py>=1.1.0
Requires-Dist: PyYAML>=5.1.0
Requires-Dist: paramiko>=2.0.1
Requires-Dist: GitPython>=2.1.8
Requires-Dist: python-daemon>=2.0.4
Requires-Dist: extras
Requires-Dist: statsd>=3.0
Requires-Dist: prometheus-client
Requires-Dist: voluptuous>=0.10.2
Requires-Dist: apscheduler>=3.0
Requires-Dist: tzlocal<3.0
Requires-Dist: PrettyTable
Requires-Dist: babel>=1.0
Requires-Dist: netaddr
Requires-Dist: kazoo==2.9.0
Requires-Dist: sqlalchemy>=2.0.0
Requires-Dist: alembic
Requires-Dist: cryptography>=39.0.0
Requires-Dist: cachecontrol
Requires-Dist: cachetools
Requires-Dist: pyjwt>=2.5.0
Requires-Dist: psutil
Requires-Dist: google-re2>=1.1
Requires-Dist: paho-mqtt<2.0.0
Requires-Dist: cherrypy
Requires-Dist: ws4py
Requires-Dist: routes
Requires-Dist: jsonpath-rw
Requires-Dist: urllib3!=1.25.4,!=1.25.5
Requires-Dist: cheroot<11.0.0
Requires-Dist: elasticsearch<8.0.0
Requires-Dist: PyMySQL
Requires-Dist: psycopg2-binary
Requires-Dist: opentelemetry-sdk>=1.25.0
Requires-Dist: grpcio==1.69.0
Requires-Dist: opentelemetry-exporter-otlp-proto-grpc>=1.25.0
Requires-Dist: opentelemetry-exporter-otlp-proto-http>=1.25.0
Requires-Dist: confluent-kafka<2.8.1
Requires-Dist: google-api-core<2.28.0
Requires-Dist: google-cloud-pubsub
Requires-Dist: openstacksdk!=2.0.0,>=0.103.0
Requires-Dist: rackspaceauth
Requires-Dist: openshift
Requires-Dist: boto3>=1.20.0
Requires-Dist: google-api-python-client
Requires-Dist: ibm-vpc
Requires-Dist: ibm-platform-services
Requires-Dist: ibm-cos-sdk>=2.11.0
Requires-Dist: mmh3
Provides-Extra: zuul-base
Requires-Dist: yappi; extra == "zuul-base"
Requires-Dist: objgraph; extra == "zuul-base"
Requires-Dist: python-logstash-async; extra == "zuul-base"
Provides-Extra: test
Requires-Dist: coverage>=3.6; extra == "test"
Requires-Dist: fixtures>=0.3.14; extra == "test"
Requires-Dist: stestr>=1.0.0; extra == "test"
Requires-Dist: testtools>=0.9.32; extra == "test"
Requires-Dist: graphql-core<=3.2.6; extra == "test"
Requires-Dist: PyMySQL; extra == "test"
Requires-Dist: psycopg2-binary; extra == "test"
Requires-Dist: beautifulsoup4; extra == "test"
Requires-Dist: graphene; extra == "test"
Requires-Dist: requests_mock; extra == "test"
Requires-Dist: moto<5.1.17; extra == "test"
Dynamic: author
Dynamic: author-email
Dynamic: classifier
Dynamic: description
Dynamic: home-page
Dynamic: license-file
Dynamic: provides-extra
Dynamic: requires-dist
Dynamic: requires-python
Dynamic: summary
